Tokenization_Uzbek/AffixTokenizer.py
Tokenization_Uzbek/CharTokenizer.py
Tokenization_Uzbek/PhraseTokenizer.py
Tokenization_Uzbek/SyllableTokenizer.py
Tokenization_Uzbek/WordTokenizer.py
Tokenization_Uzbek/__init__.py
UzbekTokenization/AffixTokenizer.py
UzbekTokenization/CharTokenizer.py
UzbekTokenization/PhraseTokenizer.py
UzbekTokenization/SyllableTokenizer.py
UzbekTokenization/WordTokenizer.py
UzbekTokenization/WordTokenizer_.py
UzbekTokenization/__init__.py
uzbektokenization-2.0.dist-info/METADATA
uzbektokenization-2.0.dist-info/WHEEL
uzbektokenization-2.0.dist-info/top_level.txt
uzbektokenization-2.0.dist-info/RECORD
