Metadata-Version: 2.1
Name: uzbektokenization
Version: 2.0
Summary: A package designed for segmenting Uzbek texts into (a) words (with compound words and phrases), (b) syllables, (c) affixes, and (d) characters.
Home-page: https://github.com/ddasturbek/UzbekTokenization
Author: dasturbek
Author-email: sobirovogabek0409@gmail.com
Classifier: Programming Language :: Python :: 3
Classifier: License :: OSI Approved :: MIT License
Classifier: Operating System :: OS Independent
Requires-Python: >=3.6
